nimastparser/__init__.py
nimastpaser-1.0.1.dist-info/METADATA
nimastpaser-1.0.1.dist-info/WHEEL
nimastpaser-1.0.1.dist-info/top_level.txt
nimastpaser-1.0.1.dist-info/RECORD
