Metadata-Version: 2.1
Name: nimastpaser
Version: 1.0.1
Summary: Python Package made by Mhadhbi Issam . 
Home-page: https://gitlab.com/game-dev-comapny/libraries/nimastparser.git
Author: $GITLAB_USER_LOGIN
Author-email: mhadhbixissam@gmail.com
Project-URL: Documentation, https://pydefold.readthedocs.io/en/latest/
Classifier: Programming Language :: Python :: 3
Classifier: License :: OSI Approved :: MIT License
Classifier: Operating System :: OS Independent
Requires-Dist: Pydefold ==1.2.5
Requires-Dist: gitpython
Requires-Dist: jinja2
